CHANGELOG
MANIFEST.in
README.rst
omitted.py
setup.py
omitted.egg-info/PKG-INFO
omitted.egg-info/SOURCES.txt
omitted.egg-info/dependency_links.txt
omitted.egg-info/not-zip-safe
omitted.egg-info/top_level.txt