Metadata-Version: 1.0
Name: omitted
Version: 0.1.2
Summary: A Do-Not-Care Value for Python
Home-page: https://github.com/rconradharris/omitted
Author: Rick Harris
Author-email: rconradharris@gmail.com
License: MIT
Platform: any
Classifier: Environment :: Web Environment
Classifier: Intended Audience :: Developers
Classifier: License :: OSI Approved :: MIT License
Classifier: Operating System :: OS Independent
Classifier: Programming Language :: Python
Classifier: Topic :: Internet :: WWW/HTTP :: Dynamic Content
Classifier: Topic :: Software Development :: Libraries :: Python Modules
